splitit/__init__.py
splitit/api_client.py
splitit/configuration.py
splitit/rest.py
splitit/api/__init__.py
splitit/api/create_installment_plan_api.py
splitit/api/info_api.py
splitit/api/infrastructure_api.py
splitit/api/installment_plan_api.py
splitit/api/login_api.py
splitit/models/__init__.py
splitit/models/address_data.py
splitit/models/address_data2.py
splitit/models/amount_details.py
splitit/models/amount_details2.py
splitit/models/approve_installment_plan_request.py
splitit/models/authentication_type.py
splitit/models/cancel_installment_plan_request.py
splitit/models/card_brand.py
splitit/models/card_data.py
splitit/models/card_result.py
splitit/models/card_type.py
splitit/models/cart_data.py
splitit/models/chargeback_request.py
splitit/models/consumer_data.py
splitit/models/create_installment_plan_legacy_response.py
splitit/models/create_installment_plan_request.py
splitit/models/create_installments_plan_response.py
splitit/models/currency.py
splitit/models/delay_resolution.py
splitit/models/dispute_status.py
splitit/models/disputes.py
splitit/models/error.py
splitit/models/events_endpoints.py
splitit/models/extended_currency.py
splitit/models/external_auth.py
splitit/models/fraud_check.py
splitit/models/fraud_check_result.py
splitit/models/get3_d_secure_parameters_request.py
splitit/models/get3_d_secure_parameters_response.py
splitit/models/get_fraud_status_display_request.py
splitit/models/get_fraud_status_display_response.py
splitit/models/get_initiated_installment_plan_request.py
splitit/models/get_initiated_installment_plan_response.py
splitit/models/get_initiated_update_payment_data_response.py
splitit/models/get_installment_schedules_request.py
splitit/models/get_installments_plan_extended_response.py
splitit/models/get_installments_plan_response.py
splitit/models/get_installments_plan_search_criteria_request.py
splitit/models/get_installments_schedule_response.py
splitit/models/get_pgtl_request.py
splitit/models/get_pgtl_response.py
splitit-1.6.10.dist-info/METADATA
splitit-1.6.10.dist-info/WHEEL
splitit-1.6.10.dist-info/top_level.txt
splitit-1.6.10.dist-info/RECORD
