Metadata-Version: 2.1
Name: splitit
Version: 1.6.10
Summary: Splitit Transactional SDK
Home-page: https://github.com/Splitit/Splitit.SDKs.Python
Author: UNKNOWN
Author-email: support@splitit.com
License: UNKNOWN
Keywords: Swagger,splitit,SDK
Platform: UNKNOWN
Requires-Dist: certifi (>=2017.4.17)
Requires-Dist: python-dateutil (>=2.1)
Requires-Dist: six (>=1.10)
Requires-Dist: urllib3 (>=1.23)
